[
	{
		"id": 201,
		"name": "Iola",
		"surname": "Powers",
		"phone": "018-139-4717",
		"email": "ante.blandit@outlook.edu",
		"birth_date": "Mar 20, 2000",
		"country": "Canada",
		"city": "Rigolet",
		"postal_code": "V6T 6M7",
		"address": "154-5415 Auctor St."
	},
	{
		"id": 202,
		"name": "Maxwell",
		"surname": "Holden",
		"phone": "045-402-7693",
		"email": "donec@hotmail.edu",
		"birth_date": "Dec 2, 1986",
		"country": "Canada",
		"city": "Murdochville",
		"postal_code": "S7E 6E0",
		"address": "Ap #880-6372 Ultrices. St."
	},
	{
		"id": 203,
		"name": "Jarrod",
		"surname": "Fields",
		"phone": "010-741-8105",
		"email": "sit.amet@google.couk",
		"birth_date": "Jan 6, 1982",
		"country": "Canada",
		"city": "Baddeck",
		"postal_code": "K3X 6Z5",
		"address": "441-8969 Rhoncus Road"
	},
	{
		"id": 204,
		"name": "Emerson",
		"surname": "Sharp",
		"phone": "068-138-9383",
		"email": "ante.iaculis@outlook.ca",
		"birth_date": "Oct 15, 1994",
		"country": "Canada",
		"city": "Maple Creek",
		"postal_code": "Y2C 9E6",
		"address": "517-6759 Ut, Av."
	},
	{
		"id": 205,
		"name": "Sonya",
		"surname": "Mckee",
		"phone": "041-151-9737",
		"email": "magna.phasellus.dolor@google.ca",
		"birth_date": "May 7, 1983",
		"country": "Canada",
		"city": "Dieppe",
		"postal_code": "E7S 4P8",
		"address": "Ap #916-8051 A St."
	},
	{
		"id": 206,
		"name": "Harper",
		"surname": "Hart",
		"phone": "030-656-1670",
		"email": "fringilla.donec@outlook.net",
		"birth_date": "Nov 17, 2000",
		"country": "Canada",
		"city": "Québec City",
		"postal_code": "B4K 0J6",
		"address": "8588 Massa. Ave"
	},
	{
		"id": 207,
		"name": "Yvonne",
		"surname": "Hatfield",
		"phone": "003-854-1445",
		"email": "magna.et.ipsum@google.edu",
		"birth_date": "Sep 22, 1981",
		"country": "Canada",
		"city": "Rae-Edzo",
		"postal_code": "20Y 8L2",
		"address": "Ap #636-8055 Egestas St."
	},
	{
		"id": 208,
		"name": "Burke",
		"surname": "Graham",
		"phone": "064-568-4454",
		"email": "vel@yahoo.org",
		"birth_date": "Feb 23, 1993",
		"country": "Canada",
		"city": "Annapolis Royal",
		"postal_code": "S4Y 8V5",
		"address": "Ap #983-6042 Amet Street"
	},
	{
		"id": 209,
		"name": "Athena",
		"surname": "Malone",
		"phone": "027-280-8275",
		"email": "pellentesque.tincidunt@yahoo.ca",
		"birth_date": "Dec 14, 1991",
		"country": "Canada",
		"city": "Cambridge Bay",
		"postal_code": "93Z 5S5",
		"address": "Ap #388-8542 Est St."
	},
	{
		"id": 210,
		"name": "Slade",
		"surname": "Poole",
		"phone": "084-771-1363",
		"email": "amet@icloud.com",
		"birth_date": "Feb 16, 2001",
		"country": "Canada",
		"city": "Ottawa",
		"postal_code": "A1S 9W6",
		"address": "601-6142 Etiam St."
	},
	{
		"id": 211,
		"name": "Larissa",
		"surname": "Carpenter",
		"phone": "066-617-3711",
		"email": "congue@aol.org",
		"birth_date": "Jan 21, 1998",
		"country": "Canada",
		"city": "Cumberland",
		"postal_code": "S5Y 2L8",
		"address": "7285 Sed St."
	},
	{
		"id": 212,
		"name": "Zeph",
		"surname": "Schmidt",
		"phone": "056-157-7412",
		"email": "vestibulum.lorem@hotmail.ca",
		"birth_date": "Apr 10, 1986",
		"country": "Canada",
		"city": "Fort Smith",
		"postal_code": "V3G 8B3",
		"address": "4756 Tempor Rd."
	},
	{
		"id": 213,
		"name": "Blake",
		"surname": "Strickland",
		"phone": "067-339-3024",
		"email": "ac.libero.nec@yahoo.com",
		"birth_date": "Apr 15, 1983",
		"country": "Canada",
		"city": "Mission",
		"postal_code": "R0V 9R2",
		"address": "P.O. Box 207, 6843 Imperdiet Avenue"
	},
	{
		"id": 214,
		"name": "Cleo",
		"surname": "George",
		"phone": "026-867-1198",
		"email": "pellentesque.habitant@outlook.net",
		"birth_date": "Dec 24, 1998",
		"country": "Canada",
		"city": "Kakisa",
		"postal_code": "R6W 8G7",
		"address": "Ap #266-9424 Orci St."
	},
	{
		"id": 215,
		"name": "Keegan",
		"surname": "Watson",
		"phone": "058-771-3718",
		"email": "interdum.enim.non@protonmail.edu",
		"birth_date": "May 2, 1996",
		"country": "Canada",
		"city": "Oxford County",
		"postal_code": "S7H 0G4",
		"address": "270-2964 Aliquet Avenue"
	},
	{
		"id": 216,
		"name": "Tana",
		"surname": "Stout",
		"phone": "035-569-5523",
		"email": "et.magnis.dis@aol.net",
		"birth_date": "Jun 28, 1983",
		"country": "Canada",
		"city": "Municipal District",
		"postal_code": "D6Y 8V7",
		"address": "7884 Vulputate Rd."
	},
	{
		"id": 217,
		"name": "Avye",
		"surname": "Key",
		"phone": "016-727-3427",
		"email": "non.dui@yahoo.net",
		"birth_date": "Mar 16, 1987",
		"country": "Canada",
		"city": "Marystown",
		"postal_code": "37N 1N0",
		"address": "P.O. Box 712, 8627 Mi Rd."
	},
	{
		"id": 218,
		"name": "Sonia",
		"surname": "Dejesus",
		"phone": "091-540-1865",
		"email": "ipsum.porta@google.edu",
		"birth_date": "Jun 13, 1997",
		"country": "Canada",
		"city": "Fredericton",
		"postal_code": "H6H 1C1",
		"address": "231-8704 Tempor Ave"
	},
	{
		"id": 219,
		"name": "Ivan",
		"surname": "Saunders",
		"phone": "036-230-9218",
		"email": "egestas.blandit.nam@icloud.org",
		"birth_date": "Jul 7, 1985",
		"country": "Canada",
		"city": "Houston",
		"postal_code": "b5M 0E6",
		"address": "350-1489 Sit Road"
	},
	{
		"id": 220,
		"name": "Martha",
		"surname": "Roth",
		"phone": "077-482-6236",
		"email": "semper.rutrum@yahoo.edu",
		"birth_date": "Apr 5, 1994",
		"country": "Canada",
		"city": "Gander",
		"postal_code": "A3X 8E4",
		"address": "Ap #179-4366 Pellentesque St."
	},
	{
		"id": 221,
		"name": "Sasha",
		"surname": "Emerson",
		"phone": "024-226-4281",
		"email": "tempor.augue.ac@icloud.couk",
		"birth_date": "Aug 24, 1981",
		"country": "Canada",
		"city": "Watson Lake",
		"postal_code": "H3X 9N3",
		"address": "885-8605 Egestas Rd."
	},
	{
		"id": 222,
		"name": "Theodore",
		"surname": "Barry",
		"phone": "098-447-1583",
		"email": "at.pede.cras@google.ca",
		"birth_date": "Feb 16, 1983",
		"country": "Canada",
		"city": "Ucluelet",
		"postal_code": "B2C 5H2",
		"address": "786-2757 Diam Rd."
	},
	{
		"id": 223,
		"name": "Linus",
		"surname": "Willis",
		"phone": "056-347-2535",
		"email": "ultrices.posuere@yahoo.couk",
		"birth_date": "Mar 23, 1992",
		"country": "Canada",
		"city": "Lourdes",
		"postal_code": "B0R 4L1",
		"address": "6491 Cursus St."
	},
	{
		"id": 224,
		"name": "Raymond",
		"surname": "Oneil",
		"phone": "001-668-7183",
		"email": "lorem@outlook.ca",
		"birth_date": "Jan 21, 1987",
		"country": "Canada",
		"city": "Watson Lake",
		"postal_code": "E9K 1S7",
		"address": "172 Enim. St."
	},
	{
		"id": 225,
		"name": "Ursa",
		"surname": "Kelly",
		"phone": "007-454-7455",
		"email": "vitae.diam@icloud.ca",
		"birth_date": "Aug 21, 1996",
		"country": "Canada",
		"city": "West Vancouver",
		"postal_code": "T0G 8G4",
		"address": "540-895 Bibendum. Avenue"
	},
	{
		"id": 226,
		"name": "Willa",
		"surname": "Rowland",
		"phone": "011-259-1714",
		"email": "sociosqu.ad.litora@outlook.net",
		"birth_date": "Feb 19, 2001",
		"country": "Canada",
		"city": "Paulatuk",
		"postal_code": "S4T 5M8",
		"address": "Ap #728-8176 A, St."
	},
	{
		"id": 227,
		"name": "Idola",
		"surname": "Bowen",
		"phone": "039-398-2123",
		"email": "gravida.molestie.arcu@outlook.org",
		"birth_date": "Jan 18, 1991",
		"country": "Canada",
		"city": "Dieppe",
		"postal_code": "S1Y 5T7",
		"address": "Ap #685-1370 Curabitur Av."
	},
	{
		"id": 228,
		"name": "Leonard",
		"surname": "Davenport",
		"phone": "033-159-5147",
		"email": "venenatis@yahoo.net",
		"birth_date": "Oct 30, 1989",
		"country": "Canada",
		"city": "Beauport",
		"postal_code": "27C 8H7",
		"address": "P.O. Box 293, 261 Donec Ave"
	},
	{
		"id": 229,
		"name": "Wade",
		"surname": "Russell",
		"phone": "002-612-8695",
		"email": "ipsum@yahoo.org",
		"birth_date": "Oct 13, 1987",
		"country": "Canada",
		"city": "Guysborough",
		"postal_code": "66A 5X8",
		"address": "579-6807 Tellus Road"
	},
	{
		"id": 230,
		"name": "Dean",
		"surname": "Donovan",
		"phone": "064-828-4927",
		"email": "dolor.elit@outlook.org",
		"birth_date": "Jan 31, 1989",
		"country": "Canada",
		"city": "Cornwall",
		"postal_code": "b3C 9X8",
		"address": "346-6657 Diam Rd."
	},
	{
		"id": 231,
		"name": "Zoe",
		"surname": "Morrow",
		"phone": "039-828-3280",
		"email": "lacinia@google.com",
		"birth_date": "Oct 25, 1987",
		"country": "Canada",
		"city": "Town of Yarmouth",
		"postal_code": "S1A 9G5",
		"address": "Ap #672-8013 Natoque St."
	},
	{
		"id": 232,
		"name": "Elijah",
		"surname": "Stone",
		"phone": "035-145-1918",
		"email": "in@yahoo.net",
		"birth_date": "Jan 24, 1988",
		"country": "Canada",
		"city": "Shawinigan",
		"postal_code": "74W 5N4",
		"address": "Ap #210-4430 Donec Road"
	},
	{
		"id": 233,
		"name": "Griffith",
		"surname": "Golden",
		"phone": "056-674-6383",
		"email": "nunc@yahoo.org",
		"birth_date": "Dec 4, 1989",
		"country": "Canada",
		"city": "Municipal District",
		"postal_code": "53S 8R5",
		"address": "190-7471 Dolor. Street"
	},
	{
		"id": 234,
		"name": "Camilla",
		"surname": "Roach",
		"phone": "011-421-2427",
		"email": "tristique.senectus@hotmail.edu",
		"birth_date": "Feb 27, 1993",
		"country": "Canada",
		"city": "Brandon",
		"postal_code": "R2E 1C9",
		"address": "Ap #858-5803 Praesent Street"
	},
	{
		"id": 235,
		"name": "Medge",
		"surname": "Nieves",
		"phone": "044-518-5071",
		"email": "ac@icloud.couk",
		"birth_date": "Jun 11, 1993",
		"country": "Canada",
		"city": "Ponoka",
		"postal_code": "H7R 2T8",
		"address": "561-787 Pellentesque Street"
	},
	{
		"id": 236,
		"name": "Gemma",
		"surname": "Calderon",
		"phone": "049-527-1060",
		"email": "in.faucibus.morbi@aol.edu",
		"birth_date": "Nov 12, 1989",
		"country": "Canada",
		"city": "Champlain",
		"postal_code": "S4J 1P5",
		"address": "983-9057 Integer Av."
	},
	{
		"id": 237,
		"name": "Drake",
		"surname": "Walsh",
		"phone": "048-338-9721",
		"email": "libero.integer@google.edu",
		"birth_date": "Jan 22, 1984",
		"country": "Canada",
		"city": "Flin Flon",
		"postal_code": "f8T 7B4",
		"address": "P.O. Box 511, 7500 Interdum Ave"
	},
	{
		"id": 238,
		"name": "Chester",
		"surname": "Haynes",
		"phone": "059-783-3104",
		"email": "ut@protonmail.edu",
		"birth_date": "Sep 13, 1988",
		"country": "Canada",
		"city": "Cochrane",
		"postal_code": "74M 8T1",
		"address": "P.O. Box 284, 9364 Ultrices St."
	},
	{
		"id": 239,
		"name": "Melissa",
		"surname": "Cameron",
		"phone": "012-127-5563",
		"email": "quisque.varius@protonmail.ca",
		"birth_date": "Feb 21, 1992",
		"country": "Canada",
		"city": "Beausejour",
		"postal_code": "B0K 2P6",
		"address": "Ap #147-7582 Ante St."
	},
	{
		"id": 240,
		"name": "Jada",
		"surname": "Porter",
		"phone": "074-247-8256",
		"email": "condimentum.donec@aol.ca",
		"birth_date": "Sep 8, 1987",
		"country": "Canada",
		"city": "North Vancouver",
		"postal_code": "R5L 6C1",
		"address": "P.O. Box 557, 8889 Erat Rd."
	},
	{
		"id": 241,
		"name": "Xandra",
		"surname": "Spencer",
		"phone": "016-322-6574",
		"email": "cursus.in@outlook.net",
		"birth_date": "Jun 22, 1989",
		"country": "Canada",
		"city": "Fraser-Fort George",
		"postal_code": "P1B 8C8",
		"address": "P.O. Box 848, 3751 Ante, Road"
	},
	{
		"id": 242,
		"name": "Neville",
		"surname": "Donovan",
		"phone": "027-122-5812",
		"email": "ac@protonmail.edu",
		"birth_date": "May 21, 1988",
		"country": "Canada",
		"city": "Cape Breton Island",
		"postal_code": "R8H 1V7",
		"address": "326-1559 Nunc. Avenue"
	},
	{
		"id": 243,
		"name": "Alan",
		"surname": "Vazquez",
		"phone": "084-548-5311",
		"email": "sapien.gravida.non@protonmail.couk",
		"birth_date": "Jun 17, 1996",
		"country": "Canada",
		"city": "Fort Good Hope",
		"postal_code": "41T 4T0",
		"address": "697-3023 Donec Road"
	},
	{
		"id": 244,
		"name": "Andrew",
		"surname": "Strong",
		"phone": "037-676-0570",
		"email": "nulla.at@google.ca",
		"birth_date": "May 17, 1997",
		"country": "Canada",
		"city": "Watson Lake",
		"postal_code": "Z1B 9R8",
		"address": "P.O. Box 961, 5209 Ridiculus Av."
	},
	{
		"id": 245,
		"name": "Iola",
		"surname": "Griffith",
		"phone": "081-781-2806",
		"email": "magna@protonmail.couk",
		"birth_date": "May 5, 1995",
		"country": "Canada",
		"city": "Penticton",
		"postal_code": "A2E 1B5",
		"address": "P.O. Box 912, 8949 Quis Avenue"
	},
	{
		"id": 246,
		"name": "Lewis",
		"surname": "Lynn",
		"phone": "061-978-2835",
		"email": "consectetuer.adipiscing@outlook.edu",
		"birth_date": "Jun 13, 1979",
		"country": "Canada",
		"city": "Neuville",
		"postal_code": "20N 5E1",
		"address": "Ap #549-4391 Dapibus St."
	},
	{
		"id": 247,
		"name": "Olga",
		"surname": "Case",
		"phone": "083-633-4683",
		"email": "turpis@yahoo.edu",
		"birth_date": "Jul 4, 1991",
		"country": "Canada",
		"city": "Lions Bay",
		"postal_code": "N1J 8P7",
		"address": "P.O. Box 140, 3589 Vestibulum. Ave"
	},
	{
		"id": 248,
		"name": "Allen",
		"surname": "Calhoun",
		"phone": "024-836-3222",
		"email": "ipsum.non@outlook.ca",
		"birth_date": "Nov 1, 1987",
		"country": "Canada",
		"city": "Cambridge Bay",
		"postal_code": "N7J 8S7",
		"address": "Ap #698-8629 Nulla Street"
	},
	{
		"id": 249,
		"name": "Rhea",
		"surname": "Harvey",
		"phone": "052-042-5654",
		"email": "proin@protonmail.org",
		"birth_date": "Jul 2, 1997",
		"country": "Canada",
		"city": "Weyburn",
		"postal_code": "j7L 2S9",
		"address": "910-7903 Habitant Avenue"
	},
	{
		"id": 250,
		"name": "Hilda",
		"surname": "Levy",
		"phone": "088-867-5267",
		"email": "et.libero@yahoo.org",
		"birth_date": "Dec 21, 1994",
		"country": "Canada",
		"city": "Baddeck",
		"postal_code": "B4R 5C5",
		"address": "P.O. Box 306, 6953 At Street"
	},
	{
		"id": 251,
		"name": "Zane",
		"surname": "Collier",
		"phone": "098-548-1455",
		"email": "in.aliquet.lobortis@icloud.com",
		"birth_date": "Aug 25, 1980",
		"country": "Canada",
		"city": "Beaconsfield",
		"postal_code": "H4Y 6Y2",
		"address": "P.O. Box 309, 103 Neque Street"
	},
	{
		"id": 252,
		"name": "Zephania",
		"surname": "Collins",
		"phone": "031-817-1549",
		"email": "urna.vivamus@icloud.ca",
		"birth_date": "Jun 29, 1994",
		"country": "Canada",
		"city": "Arviat",
		"postal_code": "Y8X 0E8",
		"address": "237-5532 Donec St."
	},
	{
		"id": 253,
		"name": "Keane",
		"surname": "Parks",
		"phone": "048-303-4775",
		"email": "consectetuer.adipiscing@google.edu",
		"birth_date": "Oct 2, 1986",
		"country": "Canada",
		"city": "Town of Yarmouth",
		"postal_code": "T2R 4Z7",
		"address": "793-2776 Ornare St."
	},
	{
		"id": 254,
		"name": "John",
		"surname": "Cotton",
		"phone": "085-253-4901",
		"email": "diam@yahoo.org",
		"birth_date": "Sep 26, 1983",
		"country": "Canada",
		"city": "Colwood",
		"postal_code": "53K 8S9",
		"address": "Ap #324-6329 Ipsum Road"
	},
	{
		"id": 255,
		"name": "Blaze",
		"surname": "Daniel",
		"phone": "087-870-8309",
		"email": "felis@protonmail.org",
		"birth_date": "Oct 11, 1998",
		"country": "Canada",
		"city": "Swan Hills",
		"postal_code": "Y1N 5X1",
		"address": "811-6644 Id, Road"
	},
	{
		"id": 256,
		"name": "Lane",
		"surname": "Paul",
		"phone": "044-254-6877",
		"email": "nec.euismod@aol.edu",
		"birth_date": "Aug 10, 1983",
		"country": "Canada",
		"city": "Saskatoon",
		"postal_code": "T3J 3X5",
		"address": "P.O. Box 850, 1002 Purus. Av."
	},
	{
		"id": 257,
		"name": "Heather",
		"surname": "Burks",
		"phone": "053-588-8671",
		"email": "primis.in@protonmail.com",
		"birth_date": "Oct 13, 1994",
		"country": "Canada",
		"city": "Dieppe",
		"postal_code": "86W 9G5",
		"address": "Ap #966-2226 Congue, Street"
	},
	{
		"id": 258,
		"name": "Stone",
		"surname": "Robbins",
		"phone": "076-226-5738",
		"email": "tempus.eu.ligula@google.edu",
		"birth_date": "Jun 26, 1980",
		"country": "Canada",
		"city": "Caledon",
		"postal_code": "R4R 6Y3",
		"address": "Ap #169-3524 Quam Street"
	},
	{
		"id": 259,
		"name": "Slade",
		"surname": "Downs",
		"phone": "034-228-4880",
		"email": "nunc@protonmail.net",
		"birth_date": "May 28, 1994",
		"country": "Canada",
		"city": "Minitonas",
		"postal_code": "T2Y 5Z1",
		"address": "Ap #219-2963 Tristique Road"
	},
	{
		"id": 260,
		"name": "Grace",
		"surname": "Rowe",
		"phone": "071-756-4297",
		"email": "convallis.convallis@hotmail.edu",
		"birth_date": "Mar 25, 1987",
		"country": "Canada",
		"city": "Abbotsford",
		"postal_code": "Y7S 3W6",
		"address": "Ap #417-5793 Tincidunt Rd."
	},
	{
		"id": 261,
		"name": "Violet",
		"surname": "Weber",
		"phone": "019-661-3744",
		"email": "aliquet.metus@hotmail.couk",
		"birth_date": "Sep 23, 1984",
		"country": "Canada",
		"city": "Ucluelet",
		"postal_code": "W4C 3H8",
		"address": "102-5355 Aliquet. Av."
	},
	{
		"id": 262,
		"name": "Brett",
		"surname": "Kirby",
		"phone": "076-166-2169",
		"email": "auctor.nunc.nulla@outlook.org",
		"birth_date": "Dec 12, 1988",
		"country": "Canada",
		"city": "Banff",
		"postal_code": "S6V 7V5",
		"address": "Ap #431-3047 Adipiscing Rd."
	},
	{
		"id": 263,
		"name": "Ima",
		"surname": "Hendricks",
		"phone": "065-953-8795",
		"email": "diam.proin@icloud.net",
		"birth_date": "Nov 6, 1990",
		"country": "Canada",
		"city": "Whitehorse",
		"postal_code": "78V 0B5",
		"address": "Ap #750-483 Lorem, Rd."
	},
	{
		"id": 264,
		"name": "Keiko",
		"surname": "Guerra",
		"phone": "034-741-6314",
		"email": "blandit@outlook.ca",
		"birth_date": "Dec 12, 1993",
		"country": "Canada",
		"city": "Bathurst",
		"postal_code": "T7C 9N8",
		"address": "Ap #243-4259 Lectus Street"
	},
	{
		"id": 265,
		"name": "Chloe",
		"surname": "Keith",
		"phone": "022-178-1548",
		"email": "arcu.eu@protonmail.org",
		"birth_date": "Jan 10, 1999",
		"country": "Canada",
		"city": "Oliver",
		"postal_code": "B5T 7L6",
		"address": "P.O. Box 289, 3192 Cursus St."
	},
	{
		"id": 266,
		"name": "Aiko",
		"surname": "Chaney",
		"phone": "026-660-1876",
		"email": "ante.ipsum.primis@protonmail.ca",
		"birth_date": "Oct 16, 1986",
		"country": "Canada",
		"city": "Vancouver",
		"postal_code": "R8S 1E1",
		"address": "821-3499 Sapien. Ave"
	},
	{
		"id": 267,
		"name": "Ocean",
		"surname": "Nelson",
		"phone": "079-481-2745",
		"email": "aenean@yahoo.com",
		"birth_date": "Dec 26, 1991",
		"country": "Canada",
		"city": "Charlottetown",
		"postal_code": "85X 3P4",
		"address": "Ap #732-8357 Pede, Rd."
	},
	{
		"id": 268,
		"name": "Clark",
		"surname": "Olson",
		"phone": "029-086-1867",
		"email": "nunc@icloud.net",
		"birth_date": "Mar 15, 1987",
		"country": "Canada",
		"city": "Montague",
		"postal_code": "S3Y 1W6",
		"address": "1315 Est Rd."
	},
	{
		"id": 269,
		"name": "Haley",
		"surname": "Fitzpatrick",
		"phone": "055-871-6664",
		"email": "in.aliquet@outlook.org",
		"birth_date": "Jan 10, 1996",
		"country": "Canada",
		"city": "Pangnirtung",
		"postal_code": "R0Y 1E3",
		"address": "P.O. Box 914, 451 Nam Rd."
	},
	{
		"id": 270,
		"name": "Elton",
		"surname": "Roberson",
		"phone": "096-325-5107",
		"email": "tristique.pharetra@google.net",
		"birth_date": "Oct 12, 1990",
		"country": "Canada",
		"city": "McCallum",
		"postal_code": "R0V 4P6",
		"address": "2857 Natoque Road"
	},
	{
		"id": 271,
		"name": "Leandra",
		"surname": "Cherry",
		"phone": "089-285-7016",
		"email": "lobortis.quis@hotmail.ca",
		"birth_date": "Sep 2, 1991",
		"country": "Canada",
		"city": "Gander",
		"postal_code": "H6S 6M9",
		"address": "554-9293 Sollicitudin Av."
	},
	{
		"id": 272,
		"name": "Hedwig",
		"surname": "Gilbert",
		"phone": "064-204-8788",
		"email": "sem.eget@icloud.edu",
		"birth_date": "Apr 16, 1991",
		"country": "Canada",
		"city": "Tuktoyaktuk",
		"postal_code": "Q4C 3G7",
		"address": "P.O. Box 496, 5145 Sapien Road"
	},
	{
		"id": 273,
		"name": "Hilary",
		"surname": "Ferguson",
		"phone": "060-710-1604",
		"email": "sapien.molestie.orci@google.edu",
		"birth_date": "Nov 3, 1981",
		"country": "Canada",
		"city": "Pangnirtung",
		"postal_code": "12T 5G4",
		"address": "Ap #736-4628 Cras St."
	},
	{
		"id": 274,
		"name": "Jameson",
		"surname": "Hunt",
		"phone": "024-732-2321",
		"email": "fringilla@protonmail.com",
		"birth_date": "Jan 29, 1982",
		"country": "Canada",
		"city": "Township of Minden Hills",
		"postal_code": "B6V 6N4",
		"address": "224-4927 Praesent Ave"
	},
	{
		"id": 275,
		"name": "Kenyon",
		"surname": "Hartman",
		"phone": "082-871-7248",
		"email": "convallis.ante.lectus@yahoo.com",
		"birth_date": "Aug 3, 1982",
		"country": "Canada",
		"city": "Richmond",
		"postal_code": "R8H 2K2",
		"address": "8564 Facilisi. St."
	}
]